code_spyder/__init__.py
code_spyder/__main__.py
code_spyder/spyder.py
code_spyder-1.0.1.dist-info/LICENSE
code_spyder-1.0.1.dist-info/METADATA
code_spyder-1.0.1.dist-info/WHEEL
code_spyder-1.0.1.dist-info/entry_points.txt
code_spyder-1.0.1.dist-info/top_level.txt
code_spyder-1.0.1.dist-info/RECORD
